<annotation>
    <folder>train</folder>
    <filename>1460.jpg</filename>
    <path>/Users/chadd/Documents/Chadd/Work/DSO/Model Re-training/TensorFlow/workspace/training/images/train/1460.jpg</path>
    <source>
        <database>Unknown</database>
    </source>
    <size>
        <width>256</width>
        <height>256</height>
        <depth>3</depth>
    </size>
    <segmented>0</segmented>
    <object>
        <name>bird</name>
        <pose>Unspecified</pose>
        <truncated>0</truncated>
        <difficult>0</difficult>
        <bndbox>
            <xmin>145</xmin>
            <ymin>115</ymin>
            <xmax>171</xmax>
            <ymax>141</ymax>
        </bndbox>
    </object>    <object>
        <name>airplane</name>
        <pose>Unspecified</pose>
        <truncated>0</truncated>
        <difficult>0</difficult>
        <bndbox>
            <xmin>68</xmin>
            <ymin>22</ymin>
            <xmax>106</xmax>
            <ymax>60</ymax>
        </bndbox>
    </object>    <object>
        <name>automobile</name>
        <pose>Unspecified</pose>
        <truncated>0</truncated>
        <difficult>0</difficult>
        <bndbox>
            <xmin>160</xmin>
            <ymin>49</ymin>
            <xmax>192</xmax>
            <ymax>81</ymax>
        </bndbox>
    </object>    <object>
        <name>bird</name>
        <pose>Unspecified</pose>
        <truncated>0</truncated>
        <difficult>0</difficult>
        <bndbox>
            <xmin>0</xmin>
            <ymin>190</ymin>
            <xmax>16</xmax>
            <ymax>206</ymax>
        </bndbox>
    </object>    <object>
        <name>cat</name>
        <pose>Unspecified</pose>
        <truncated>0</truncated>
        <difficult>0</difficult>
        <bndbox>
            <xmin>211</xmin>
            <ymin>69</ymin>
            <xmax>243</xmax>
            <ymax>101</ymax>
        </bndbox>
    </object>    <object>
        <name>truck</name>
        <pose>Unspecified</pose>
        <truncated>0</truncated>
        <difficult>0</difficult>
        <bndbox>
            <xmin>8</xmin>
            <ymin>113</ymin>
            <xmax>46</xmax>
            <ymax>151</ymax>
        </bndbox>
    </object>    <object>
        <name>automobile</name>
        <pose>Unspecified</pose>
        <truncated>0</truncated>
        <difficult>0</difficult>
        <bndbox>
            <xmin>34</xmin>
            <ymin>156</ymin>
            <xmax>69</xmax>
            <ymax>191</ymax>
        </bndbox>
    </object>    <object>
        <name>dog</name>
        <pose>Unspecified</pose>
        <truncated>0</truncated>
        <difficult>0</difficult>
        <bndbox>
            <xmin>116</xmin>
            <ymin>128</ymin>
            <xmax>142</xmax>
            <ymax>154</ymax>
        </bndbox>
    </object>    <object>
        <name>ship</name>
        <pose>Unspecified</pose>
        <truncated>0</truncated>
        <difficult>0</difficult>
        <bndbox>
            <xmin>35</xmin>
            <ymin>11</ymin>
            <xmax>67</xmax>
            <ymax>43</ymax>
        </bndbox>
    </object>    <object>
        <name>frog</name>
        <pose>Unspecified</pose>
        <truncated>0</truncated>
        <difficult>0</difficult>
        <bndbox>
            <xmin>39</xmin>
            <ymin>215</ymin>
            <xmax>71</xmax>
            <ymax>247</ymax>
        </bndbox>
    </object>    <object>
        <name>ship</name>
        <pose>Unspecified</pose>
        <truncated>0</truncated>
        <difficult>0</difficult>
        <bndbox>
            <xmin>105</xmin>
            <ymin>182</ymin>
            <xmax>121</xmax>
            <ymax>198</ymax>
        </bndbox>
    </object>    <object>
        <name>frog</name>
        <pose>Unspecified</pose>
        <truncated>0</truncated>
        <difficult>0</difficult>
        <bndbox>
            <xmin>125</xmin>
            <ymin>192</ymin>
            <xmax>160</xmax>
            <ymax>227</ymax>
        </bndbox>
    </object>    <object>
        <name>ship</name>
        <pose>Unspecified</pose>
        <truncated>0</truncated>
        <difficult>0</difficult>
        <bndbox>
            <xmin>82</xmin>
            <ymin>141</ymin>
            <xmax>114</xmax>
            <ymax>173</ymax>
        </bndbox>
    </object>    <object>
        <name>deer</name>
        <pose>Unspecified</pose>
        <truncated>0</truncated>
        <difficult>0</difficult>
        <bndbox>
            <xmin>75</xmin>
            <ymin>183</ymin>
            <xmax>104</xmax>
            <ymax>212</ymax>
        </bndbox>
    </object>    <object>
        <name>truck</name>
        <pose>Unspecified</pose>
        <truncated>0</truncated>
        <difficult>0</difficult>
        <bndbox>
            <xmin>177</xmin>
            <ymin>176</ymin>
            <xmax>215</xmax>
            <ymax>214</ymax>
        </bndbox>
    </object>    <object>
        <name>deer</name>
        <pose>Unspecified</pose>
        <truncated>0</truncated>
        <difficult>0</difficult>
        <bndbox>
            <xmin>90</xmin>
            <ymin>89</ymin>
            <xmax>128</xmax>
            <ymax>127</ymax>
        </bndbox>
    </object>    <object>
        <name>dog</name>
        <pose>Unspecified</pose>
        <truncated>0</truncated>
        <difficult>0</difficult>
        <bndbox>
            <xmin>153</xmin>
            <ymin>87</ymin>
            <xmax>175</xmax>
            <ymax>109</ymax>
        </bndbox>
    </object>    <object>
        <name>deer</name>
        <pose>Unspecified</pose>
        <truncated>0</truncated>
        <difficult>0</difficult>
        <bndbox>
            <xmin>119</xmin>
            <ymin>30</ymin>
            <xmax>151</xmax>
            <ymax>62</ymax>
        </bndbox>
    </object>    <object>
        <name>bird</name>
        <pose>Unspecified</pose>
        <truncated>0</truncated>
        <difficult>0</difficult>
        <bndbox>
            <xmin>209</xmin>
            <ymin>36</ymin>
            <xmax>241</xmax>
            <ymax>68</ymax>
        </bndbox>
    </object>    <object>
        <name>bird</name>
        <pose>Unspecified</pose>
        <truncated>0</truncated>
        <difficult>0</difficult>
        <bndbox>
            <xmin>151</xmin>
            <ymin>147</ymin>
            <xmax>173</xmax>
            <ymax>169</ymax>
        </bndbox>
    </object>
</annotation>
