<annotation>
    <folder>train</folder>
    <filename>824.jpg</filename>
    <path>/Users/chadd/Documents/Chadd/Work/DSO/Model Re-training/TensorFlow/workspace/training/images/train/824.jpg</path>
    <source>
        <database>Unknown</database>
    </source>
    <size>
        <width>256</width>
        <height>256</height>
        <depth>3</depth>
    </size>
    <segmented>0</segmented>
    <object>
        <name>deer</name>
        <pose>Unspecified</pose>
        <truncated>0</truncated>
        <difficult>0</difficult>
        <bndbox>
            <xmin>43</xmin>
            <ymin>16</ymin>
            <xmax>69</xmax>
            <ymax>42</ymax>
        </bndbox>
    </object>    <object>
        <name>frog</name>
        <pose>Unspecified</pose>
        <truncated>0</truncated>
        <difficult>0</difficult>
        <bndbox>
            <xmin>83</xmin>
            <ymin>135</ymin>
            <xmax>105</xmax>
            <ymax>157</ymax>
        </bndbox>
    </object>    <object>
        <name>ship</name>
        <pose>Unspecified</pose>
        <truncated>0</truncated>
        <difficult>0</difficult>
        <bndbox>
            <xmin>116</xmin>
            <ymin>9</ymin>
            <xmax>148</xmax>
            <ymax>41</ymax>
        </bndbox>
    </object>    <object>
        <name>ship</name>
        <pose>Unspecified</pose>
        <truncated>0</truncated>
        <difficult>0</difficult>
        <bndbox>
            <xmin>8</xmin>
            <ymin>118</ymin>
            <xmax>37</xmax>
            <ymax>147</ymax>
        </bndbox>
    </object>    <object>
        <name>truck</name>
        <pose>Unspecified</pose>
        <truncated>0</truncated>
        <difficult>0</difficult>
        <bndbox>
            <xmin>57</xmin>
            <ymin>88</ymin>
            <xmax>76</xmax>
            <ymax>107</ymax>
        </bndbox>
    </object>    <object>
        <name>bird</name>
        <pose>Unspecified</pose>
        <truncated>0</truncated>
        <difficult>0</difficult>
        <bndbox>
            <xmin>147</xmin>
            <ymin>119</ymin>
            <xmax>173</xmax>
            <ymax>145</ymax>
        </bndbox>
    </object>    <object>
        <name>bird</name>
        <pose>Unspecified</pose>
        <truncated>0</truncated>
        <difficult>0</difficult>
        <bndbox>
            <xmin>158</xmin>
            <ymin>208</ymin>
            <xmax>196</xmax>
            <ymax>246</ymax>
        </bndbox>
    </object>    <object>
        <name>airplane</name>
        <pose>Unspecified</pose>
        <truncated>0</truncated>
        <difficult>0</difficult>
        <bndbox>
            <xmin>102</xmin>
            <ymin>186</ymin>
            <xmax>121</xmax>
            <ymax>205</ymax>
        </bndbox>
    </object>    <object>
        <name>truck</name>
        <pose>Unspecified</pose>
        <truncated>0</truncated>
        <difficult>0</difficult>
        <bndbox>
            <xmin>62</xmin>
            <ymin>57</ymin>
            <xmax>81</xmax>
            <ymax>76</ymax>
        </bndbox>
    </object>    <object>
        <name>bird</name>
        <pose>Unspecified</pose>
        <truncated>0</truncated>
        <difficult>0</difficult>
        <bndbox>
            <xmin>151</xmin>
            <ymin>149</ymin>
            <xmax>173</xmax>
            <ymax>171</ymax>
        </bndbox>
    </object>    <object>
        <name>bird</name>
        <pose>Unspecified</pose>
        <truncated>0</truncated>
        <difficult>0</difficult>
        <bndbox>
            <xmin>142</xmin>
            <ymin>46</ymin>
            <xmax>161</xmax>
            <ymax>65</ymax>
        </bndbox>
    </object>    <object>
        <name>deer</name>
        <pose>Unspecified</pose>
        <truncated>0</truncated>
        <difficult>0</difficult>
        <bndbox>
            <xmin>182</xmin>
            <ymin>15</ymin>
            <xmax>204</xmax>
            <ymax>37</ymax>
        </bndbox>
    </object>    <object>
        <name>dog</name>
        <pose>Unspecified</pose>
        <truncated>0</truncated>
        <difficult>0</difficult>
        <bndbox>
            <xmin>203</xmin>
            <ymin>169</ymin>
            <xmax>229</xmax>
            <ymax>195</ymax>
        </bndbox>
    </object>    <object>
        <name>deer</name>
        <pose>Unspecified</pose>
        <truncated>0</truncated>
        <difficult>0</difficult>
        <bndbox>
            <xmin>12</xmin>
            <ymin>150</ymin>
            <xmax>47</xmax>
            <ymax>185</ymax>
        </bndbox>
    </object>    <object>
        <name>truck</name>
        <pose>Unspecified</pose>
        <truncated>0</truncated>
        <difficult>0</difficult>
        <bndbox>
            <xmin>34</xmin>
            <ymin>192</ymin>
            <xmax>60</xmax>
            <ymax>218</ymax>
        </bndbox>
    </object>    <object>
        <name>frog</name>
        <pose>Unspecified</pose>
        <truncated>0</truncated>
        <difficult>0</difficult>
        <bndbox>
            <xmin>144</xmin>
            <ymin>172</ymin>
            <xmax>170</xmax>
            <ymax>198</ymax>
        </bndbox>
    </object>    <object>
        <name>automobile</name>
        <pose>Unspecified</pose>
        <truncated>0</truncated>
        <difficult>0</difficult>
        <bndbox>
            <xmin>5</xmin>
            <ymin>61</ymin>
            <xmax>31</xmax>
            <ymax>87</ymax>
        </bndbox>
    </object>    <object>
        <name>ship</name>
        <pose>Unspecified</pose>
        <truncated>0</truncated>
        <difficult>0</difficult>
        <bndbox>
            <xmin>212</xmin>
            <ymin>71</ymin>
            <xmax>244</xmax>
            <ymax>103</ymax>
        </bndbox>
    </object>
</annotation>
